[{"pitch_id": "113101f5-12b1-496d-9446-94d865213fdb", "pitcher_id": "demo_pitcher_01", "module": "baseline-comparison", "confidence": 0.7778337514074507, "notes": null, "pitch_type": "FF", "overall_z_score": 0.6641099640588376, "top_deviations": [{"joint_index": 50, "joint_name": "joint_50", "deviation_mm": 2.0406307305160896, "z_score": 2.2727978401143263}, {"joint_index": 115, "joint_name": "joint_115", "deviation_mm": 11.635715242578064, "z_score": 1.9530513686887547}, {"joint_index": 30, "joint_name": "joint_30", "deviation_mm": 7.099098925794495, "z_score": 1.1187091927584454}, {"joint_index": 72, "joint_name": "joint_72", "deviation_mm": 3.392063383450232, "z_score": 1.9154479045188122}, {"joint_index": 53, "joint_name": "joint_53", "deviation_mm": 2.90187626009242, "z_score": 1.5079746646704892}], "is_outlier": false, "outlier_threshold": 2.5}, {"pitch_id": "113101f5-12b1-496d-9446-94d865213fdb", "pitcher_id": "demo_pitcher_01", "module": "tipping-detection", "confidence": 0.8386838745507048, "notes": null, "tip_signals": [], "max_separation_score": 0.12171253843175318, "is_tipping": false, "tipping_threshold": 0.7}, {"pitch_id": "113101f5-12b1-496d-9446-94d865213fdb", "pitcher_id": "demo_pitcher_01", "module": "fatigue-tracking", "confidence": 0.7831174029237398, "notes": null, "pitch_number_in_game": 2, "markers": [{"metric_name": "arm_slot_drop_deg", "value": 2.239072009466767, "baseline_value": 0.0, "pct_change": -1.5379523882914459}], "fatigue_score": 0.07316582415178159, "is_fatigued": false, "fatigue_threshold": 0.6}, {"pitch_id": "113101f5-12b1-496d-9446-94d865213fdb", "pitcher_id": "demo_pitcher_01", "module": "command-analysis", "confidence": 0.8754444151372804, "notes": null, "pitch_type": "FF", "plate_x": 0.19602357813136873, "plate_z": 3.4451701122386167, "release_x_deviation": 10.849184565676083, "release_z_deviation": 3.6266758268228108, "command_score": 0.5815859392959956, "zone": 3}, {"pitch_id": "113101f5-12b1-496d-9446-94d865213fdb", "pitcher_id": "demo_pitcher_01", "module": "arm-slot-drift", "confidence": 0.7548301404344896, "notes": null, "arm_slot_degrees": 40.54658710345588, "baseline_arm_slot_degrees": 38.87291854046166, "drift_degrees": 1.673668562994217, "cumulative_drift_degrees": 3.79953637630083, "is_significant_drift": false, "drift_threshold_degrees": 3.0}, {"pitch_id": "113101f5-12b1-496d-9446-94d865213fdb", "pitcher_id": "demo_pitcher_01", "module": "timing-analysis", "confidence": 0.9725091942213208, "notes": null, "pitch_type": "FF", "events": [{"event_name": "foot_plant", "frame": 15, "time_ms": 250.0, "baseline_frame": 15, "frame_delta": 0}, {"event_name": "max_hip_rotation", "frame": 35, "time_ms": 583.0, "baseline_frame": 34, "frame_delta": 1}, {"event_name": "ball_release", "frame": 48, "time_ms": 800.0, "baseline_frame": 47, "frame_delta": 1}], "timing_score": 0.9320960210012843, "is_timing_issue": false}]